cneura_ai/__init__.py
cneura_ai/agent.py
cneura_ai/agent_deploy.py
cneura_ai/agent_design.py
cneura_ai/agent_registry.py
cneura_ai/cli.py
cneura_ai/code.py
cneura_ai/config.py
cneura_ai/credential.py
cneura_ai/emotion.py
cneura_ai/executor.py
cneura_ai/llm.py
cneura_ai/logger.py
cneura_ai/memory.py
cneura_ai/messaging.py
cneura_ai/research.py
cneura_ai/shell.py
cneura_ai/tool_deploy.py
cneura_ai/tool_registry.py
cneura_ai/tools.py
cneura_ai/utils.py
cneura_ai/vad_estimate.py
cneura_ai/clients/agent_registry.py
cneura_ai/clients/auth.py
cneura_ai/clients/config.py
cneura_ai/clients/credential.py
cneura_ai/clients/knowledge_base.py
cneura_ai/clients/memory.py
cneura_ai/clients/research.py
cneura_ai/clients/shell.py
cneura_ai/clients/tool_registry.py
cneura_ai/commands/__init__.py
cneura_ai/commands/docker_runner.py
cneura_ai/commands/render.py
cneura_ai/configs/init.template.json
cneura_ai/configs/run.template.json
cneura_ai/services/agent_builder/deploy/Dockerfile
cneura_ai/services/agent_builder/deploy/main.py
cneura_ai/services/agent_builder/design/Dockerfile
cneura_ai/services/agent_builder/design/main.py
cneura_ai/services/master/client.py
cneura_ai/services/master/.venv/Lib/site-packages/cneura_ai/services/agent_builder/deploy/Dockerfile
cneura_ai/services/master/.venv/Lib/site-packages/cneura_ai/services/agent_builder/design/Dockerfile
cneura_ai/services/master/.venv/Lib/site-packages/cneura_ai/services/logger/Dockerfile
cneura_ai/services/master/.venv/Lib/site-packages/cneura_ai/services/master/.venv/Lib/site-packages/cneura_ai/services/agent_builder/deploy/Dockerfile
cneura_ai/services/master/.venv/Lib/site-packages/cneura_ai/services/master/.venv/Lib/site-packages/cneura_ai/services/agent_builder/design/Dockerfile
cneura_ai/services/master/.venv/Lib/site-packages/cneura_ai/services/master/.venv/Lib/site-packages/cneura_ai/services/logger/Dockerfile
cneura_ai-0.1.122.dist-info/licenses/LICENSE
cneura_ai-0.1.122.dist-info/METADATA
cneura_ai-0.1.122.dist-info/WHEEL
cneura_ai-0.1.122.dist-info/entry_points.txt
cneura_ai-0.1.122.dist-info/top_level.txt
cneura_ai-0.1.122.dist-info/RECORD
