Metadata-Version: 2.4
Name: cneura-ai
Version: 0.1.122
Summary: An autonomous agent orchestration framework.
Author-email: shehandezen <shehandezen@gmail.com>
Project-URL: Homepage, https://github.com/shehandezen/cneura-ai
Classifier: Programming Language :: Python :: 3
Classifier: License :: OSI Approved :: MIT License
Classifier: Operating System :: OS Independent
Requires-Python: >=3.12
License-File: LICENSE
Requires-Dist: annotated-types==0.7.0
Requires-Dist: anyio==4.9.0
Requires-Dist: asgiref==3.8.1
Requires-Dist: attrs==25.3.0
Requires-Dist: backoff==2.2.1
Requires-Dist: bcrypt==4.3.0
Requires-Dist: build==1.2.2.post1
Requires-Dist: cachetools==5.5.2
Requires-Dist: certifi==2025.4.26
Requires-Dist: cffi==1.17.1
Requires-Dist: charset-normalizer==3.4.2
Requires-Dist: Chroma==0.2.0
Requires-Dist: chroma-hnswlib==0.7.6
Requires-Dist: chromadb==1.0.7
Requires-Dist: click==8.1.8
Requires-Dist: colorama==0.4.6
Requires-Dist: coloredlogs==15.0.1
Requires-Dist: cryptography==44.0.2
Requires-Dist: Deprecated==1.2.18
Requires-Dist: distro==1.9.0
Requires-Dist: diskcache
Requires-Dist: dnspython==2.7.0
Requires-Dist: docker==7.1.0
Requires-Dist: docutils==0.21.2
Requires-Dist: durationpy==0.9
Requires-Dist: duckduckgo-search
Requires-Dist: fastapi==0.115.9
Requires-Dist: filelock==3.18.0
Requires-Dist: filetype==1.2.0
Requires-Dist: flatbuffers==25.2.10
Requires-Dist: fsspec==2025.3.2
Requires-Dist: google-ai-generativelanguage==0.6.18
Requires-Dist: google-api-core==2.24.2
Requires-Dist: google-auth==2.39.0
Requires-Dist: googleapis-common-protos==1.70.0
Requires-Dist: greenlet==3.2.1
Requires-Dist: grpcio==1.71.0
Requires-Dist: grpcio-status==1.71.0
Requires-Dist: h11==0.16.0
Requires-Dist: httpcore==1.0.9
Requires-Dist: httptools==0.6.4
Requires-Dist: httpx==0.28.1
Requires-Dist: huggingface-hub==0.30.2
Requires-Dist: humanfriendly==10.0
Requires-Dist: id==1.5.0
Requires-Dist: idna==3.10
Requires-Dist: importlib_metadata==8.6.1
Requires-Dist: importlib_resources==6.5.2
Requires-Dist: jaraco.classes==3.4.0
Requires-Dist: jaraco.context==6.0.1
Requires-Dist: jaraco.functools==4.1.0
Requires-Dist: Jinja2==3.1.6
Requires-Dist: joblib==1.4.2
Requires-Dist: jsonpatch==1.33
Requires-Dist: json5
Requires-Dist: jsonpointer==3.0.0
Requires-Dist: jsonschema==4.23.0
Requires-Dist: jsonschema-specifications==2025.4.1
Requires-Dist: keyring==25.6.0
Requires-Dist: kubernetes==32.0.1
Requires-Dist: langchain==0.3.24
Requires-Dist: langchain-core==0.3.57
Requires-Dist: langchain-google-genai==2.1.4
Requires-Dist: langchain-text-splitters==0.3.8
Requires-Dist: langsmith==0.3.40
Requires-Dist: loguru==0.7.3
Requires-Dist: markdown-it-py==3.0.0
Requires-Dist: MarkupSafe==3.0.2
Requires-Dist: mdurl==0.1.2
Requires-Dist: mmh3==5.1.0
Requires-Dist: more-itertools==10.7.0
Requires-Dist: mpmath==1.3.0
Requires-Dist: networkx==3.4.2
Requires-Dist: nh3==0.2.21
Requires-Dist: numpy==2.2.5
Requires-Dist: newspaper3k
Requires-Dist: oauthlib==3.2.2
Requires-Dist: onnxruntime==1.21.1
Requires-Dist: opentelemetry-api==1.32.1
Requires-Dist: opentelemetry-exporter-otlp-proto-common==1.32.1
Requires-Dist: opentelemetry-exporter-otlp-proto-grpc==1.32.1
Requires-Dist: opentelemetry-instrumentation==0.53b1
Requires-Dist: opentelemetry-instrumentation-asgi==0.53b1
Requires-Dist: opentelemetry-instrumentation-fastapi==0.53b1
Requires-Dist: opentelemetry-proto==1.32.1
Requires-Dist: opentelemetry-sdk==1.32.1
Requires-Dist: opentelemetry-semantic-conventions==0.53b1
Requires-Dist: opentelemetry-util-http==0.53b1
Requires-Dist: orjson==3.10.18
Requires-Dist: outcome==1.3.0.post0
Requires-Dist: overrides==7.7.0
Requires-Dist: packaging==24.2
Requires-Dist: pika==1.3.2
Requires-Dist: pillow==11.2.1
Requires-Dist: posthog==4.0.1
Requires-Dist: proto-plus==1.26.1
Requires-Dist: protobuf==5.29.4
Requires-Dist: pyasn1==0.6.1
Requires-Dist: pyasn1_modules==0.4.2
Requires-Dist: pycparser==2.22
Requires-Dist: pydantic==2.11.4
Requires-Dist: pydantic_core==2.33.2
Requires-Dist: Pygments==2.19.1
Requires-Dist: pymongo==4.12.1
Requires-Dist: PyPika==0.48.9
Requires-Dist: pyproject_hooks==1.2.0
Requires-Dist: pyreadline3==3.5.4
Requires-Dist: PySocks==1.7.1
Requires-Dist: python-dateutil==2.9.0.post0
Requires-Dist: python-dotenv==1.1.0
Requires-Dist: PyYAML==6.0.2
Requires-Dist: readme_renderer==44.0
Requires-Dist: referencing==0.36.2
Requires-Dist: regex==2024.11.6
Requires-Dist: requests==2.32.3
Requires-Dist: requests-oauthlib==2.0.0
Requires-Dist: requests-toolbelt==1.0.0
Requires-Dist: rfc3986==2.0.0
Requires-Dist: rich==14.0.0
Requires-Dist: rpds-py==0.24.0
Requires-Dist: rsa==4.9.1
Requires-Dist: safetensors==0.5.3
Requires-Dist: scikit-learn==1.6.1
Requires-Dist: scipy==1.15.2
Requires-Dist: sentence-transformers==4.1.0
Requires-Dist: setuptools==80.1.0
Requires-Dist: shellingham==1.5.4
Requires-Dist: six==1.17.0
Requires-Dist: sniffio==1.3.1
Requires-Dist: sortedcontainers==2.4.0
Requires-Dist: SQLAlchemy==2.0.40
Requires-Dist: starlette==0.45.3
Requires-Dist: stdlib-list==0.11.1
Requires-Dist: sympy==1.14.0
Requires-Dist: tenacity==9.1.2
Requires-Dist: threadpoolctl==3.6.0
Requires-Dist: tokenizers==0.21.1
Requires-Dist: torch==2.7.0
Requires-Dist: tqdm==4.67.1
Requires-Dist: transformers==4.51.3
Requires-Dist: trio==0.30.0
Requires-Dist: trio-websocket==0.12.2
Requires-Dist: twine==6.1.0
Requires-Dist: typer==0.15.3
Requires-Dist: typing-inspection==0.4.0
Requires-Dist: typing_extensions==4.13.2
Requires-Dist: urllib3==2.4.0
Requires-Dist: uvicorn==0.34.2
Requires-Dist: undetected-chromedriver
Requires-Dist: watchfiles==1.0.5
Requires-Dist: websocket-client==1.8.0
Requires-Dist: websockets==15.0.1
Requires-Dist: win32_setctime==1.2.0
Requires-Dist: wrapt==1.17.2
Requires-Dist: wsproto==1.2.0
Requires-Dist: lxml[html_clean]
Requires-Dist: yaspin
Requires-Dist: zipp==3.21.0
Requires-Dist: zstandard==0.23.0
Dynamic: license-file
